test_pluggy/__init__.py
pytest_testpluggy-0.0.1.dist-info/LICENSE
pytest_testpluggy-0.0.1.dist-info/METADATA
pytest_testpluggy-0.0.1.dist-info/WHEEL
pytest_testpluggy-0.0.1.dist-info/entry_points.txt
pytest_testpluggy-0.0.1.dist-info/top_level.txt
pytest_testpluggy-0.0.1.dist-info/RECORD
